bopy/__init__.py
bopy_cxx-0.0.1a0.dist-info/METADATA
bopy_cxx-0.0.1a0.dist-info/WHEEL
bopy_cxx-0.0.1a0.dist-info/top_level.txt
bopy_cxx-0.0.1a0.dist-info/RECORD
